{
  "task_id": "e6e9c631-8de0-494e-9ef6-fc02441be8e3",
  "original_filename": "通话录音.mp3",
  "transcript": "淘宝号码保护中哎，你好啊，你好，我这边那个回收显卡的啊，你说啊，你这边有寄了一张卡过来这边能够回收对吧啊，对的，这个卡我们这边的话有检测好的嘛，你说一下这个检测情况嘛。啊啊，你那个卡就是说这边测那个摄像的时候呢，它那个温度啊，过高了，然后的话那个啊发这边的话是比较大的，不然平时不用的话也没有注意到。我不可能我就没拆修过，怎么可能温度比较大呢？你要咱这个资产，我还在保修范围内呢。个gpu的话，温度的话是比较高的，还有一个情况的话也是要进行一个3d测试跑回的访问的时候，他那个显卡帧数的话，那个吊针的话掉的比较厉害，行驶四公里你们店我就知道有猫腻实话实说当时价格报的那么高，我就猜了有问题，那你们要砍多少钱嘛？啊，你这个卡像这种情况，我们这边的话也问了一下市场，这边了就看一下能不能处理嘛，然后基本上像这种情况的话接的人也是比较少啊，所以刚才的话也在市场这边问了其他几家了，就说你这个卡市场这边的话也是有报了一个那个价格过来啊，收的话最高的话是能收到那个1000块钱啊，你看一下是怎么处理1000块钱。啊，对对对你们你们这个卡上是真的恶心实话实说真的恶心人家给我报1800我操我我没有想到你们会这么然后如果现在问你们把卡要回来，你们肯定给我核心都换了妈的你们是真的狗啊操问题的话该什么样子的话就什么样子的啊，该什么样子什么样子？你已经把我房拆贴，什么都拆掉了，把我核心都换了。现在多一点吧，价格多一点吧。多的话，这边的话多不了兄弟，这边的话也是问了市场，这边是问了很多家了啊，1000块钱包过来的话也是最高的一个价格过来了。1000米后有限速80拍照以前还搞不了哦，最高的话这边的话就是说给你补充50块钱优惠给你我这卡连拆都没拆过啊大哥不是说你没采购他就没问题电子产品这种东西的话没有100%保证的啊，这个不排不排除是自己的购购买渠道问题。啊，这边的话能搞的话就是邮费这边帮你申请补到50块钱啊，一起的话就1050给你。我他妈的。多一点多一点，不然的话我就去淘宝那边跟你们说过。多一点吧，淘宝的话，你找淘宝的话，这边的话也是我们我们到时候来回搁，那折腾也是浪费时间，为了几百块钱再多一点吧。我也不想跟你们再掰扯了，再多一点算了，这个亏我认了。1100咯好吧，1000 1200我说过1200一公里后靠左几千个搞不了兄弟404060，你去市面上看妈的有低于1200的吗？那你还是看什么情况啊？大哥啊，我无拆销的。我，我刚才也跟你说过了电子产品，这种东西不是说没有拆修啊，电子拆我跟你说，我现在还在保修期内呢，真有问题，你们去找七彩虹官方啊我修过我修你妈，我连防拆贴都没拆我怎么修。我是说你拿去售货店那修的话，超市修过嘛，对不对你到时候拿去修的话也是会折价的嘛啊，而且你收过的东西卖的话也是确实也是比较难卖限速61100咯1100的话，这边1000 1000至少1200本来就去淘宝那边淘宝那边谈我反正商品交易记录都还在的你们这样你们这样瞎搞说实话是真的没有戏算了算了算了，主要我现在这边事情也是比较多啊，1000多1200的话就1200喽好吧，我这边的话就帮你带一下喽你发个支付宝扫码给客服喽，然后那边我那个那边麻烦给你转过去喽就这样好吧，因为这边的话，我跟客服说一下喽，你上下淘宝，然后发个收款码给客服那边好吧，不行。再多1.6百，这太低了还是太低了，真的太低了，当前车速走不了大哥，现在的话就是1000块钱啊，现在这边的话只能是给到1000块钱，那你退给我1200的话可以啊，然后现在全部拆开的嘛装好的话是3000左右邮寄回去给显卡都已经给我拆开了。啊，对对对对右侧两个车道550米后向右前方行驶，请走双独路国际这边二手岗二手岗的话是全部得拆开检测的啊，要不然你不知道啊，我走右我你妈逼即将向右前方行驶请走双独路国际会展你等着我要去淘宝那边告你前方行驶进入辅路国际会展中心出口这边的话到时候就是1000块钱，再多一点再多一点。\n这边的话到时候就是1000块钱，再多一点再多一点1200 1200，那就1200了算了算了。那你上淘宝吧，我跟客户说一下，我让他那边给你转过去，即将在红绿灯路口左转。请注意，100米后有不礼，让行人和闯红灯拍照啊。左转进入桥下道路",
  "timestamp": "2026-03-25T09:02:42.121867+00:00",
  "model_version": "TeleAI/TeleSpeechASR"
}